mydaemon/__init__.py
mydaemon-0.1.10.dist-info/LICENSE
mydaemon-0.1.10.dist-info/METADATA
mydaemon-0.1.10.dist-info/WHEEL
mydaemon-0.1.10.dist-info/top_level.txt
mydaemon-0.1.10.dist-info/RECORD
