Metadata-Version: 2.1
Name: mydaemon
Version: 0.1.10
Summary: Python daemon module
Home-page: https://github.com/emrahcom/MyDaemon
Author: emrah
Author-email: emrah.com@gmail.com
License: MIT
Keywords: daemon daemonize background service fork
Platform: UNKNOWN
Classifier: Development Status :: 4 - Beta
Classifier: Intended Audience :: Developers
Classifier: License :: OSI Approved :: MIT License
Classifier: Programming Language :: Python :: 3
Requires-Python: >=3
